{"0c5x6zlTwtO4k3YKRZsSvg==":"bodhitree-cafe-srq-logoretina-182x62.png","3QCkZse+TRuoaKUmibFfaA==":"bodhitree-cafe-srq-logoretina-1-182x62.png","osRF5mqAURI4eqDeroUChg==":"bodhi-tree-cafe-srq-logo-556x195.jpg","3OAyNGkbvuJ3c1m82j/d1g==":"gnocchi-1000x750.jpg","0rb7bvixP4j1Q9ZSe+ecqw==":"towles-court-restaurant-1920x907.jpg","8V+uwdjyaNaRs5MMkmP/1A==":"bodhitree-cafe-srq-754x677.png","atlKhWegsNdvBp9CYXHAFQ==":"hummus-960x720.jpg","jJW3PoiQ+ChZ+iO+C9hUJw==":"carolina-oscar-960x852.jpg","wSpSBpAhGHnQqIQ7pU3I4Q==":"italian-restaurant-towles-court-960x714.jpg","aO+0IdGplaI9Blm1S8CKbg==":"chicken0solare-720x960.jpg","Dgem7IJMtNlR1YdkN7AZ5Q==":"chicken0solare-568x757.jpg","/EJV12dWid+ECn/npS+vcw==":"hummus-sampler-568x703.jpg","PzDDXVxniL9oTCFpAPgUMQ==":"parmesan-cheese-salad-568x601.jpg","ZnrDi4EsH/f1ymWD3amJrQ==":"towles-court-restaurant-960x640.jpg","+x22hL0mNEessUBmVB7e3A==":"home_bodhitreecafe_sectionbg1-960x667.jpg","v/NCJthF7snu+csafvbR6A==":"bodhi-tree-menu-780x605.jpg","/EZurx56I7XJAcSVS4ZUFg==":"oscar-carolina-revelli-1080x1618.jpg","KFgchVcavyG+PmQ+1QMHQQ==":"towles-court-dinner-960x720.jpg","FuunhvvbGWz9945Ed6gg6Q==":"chicken-salad-srq-400x500.jpg","OcoppdYMPYTmditsfItXWw==":"italian-food-srq-400x400.jpg","6FVwZbK2AOiFp1S/Z952KA==":"hummus-400x500.jpg","6J0s5P8H4sRGZkqgnz/9pg==":"daily-specials-400x500.jpg","P7qlZvsTWyMJuSDkZOBNYw==":"body-tree-cafe-italian-food-400x500.jpg","+iTKC9cBipOpTtUapiiqiw==":"oscar-carolina-revelli2-1080x721.jpg","6HQmjEWGJfhIorUyHlo0Tw==":"bodhitreecafe_subheader-1920x183.png","SoSBnnbed4aqull5Gq/Zrw==":"home_bodhitreecafe_subheader1-1920x183.png","PcJki9JI/2bwqVbcq/qCdg==":"home_bodhitreecafe_sectionbg5-1920x1425.jpg","2EjX9OANjrzVKHlycYSPLQ==":"menu-1000x647.jpg","YLfRanQBkG3DFCDCOZNGeA==":"bodhi-tree-cafe-menu-2660x1722.jpg","lgQc5na+LOXk7UiSwmNSmw==":"home-banner-1920x907.jpg","Wv9DzHGpLDzqCdd53UcKLA==":"our-menu-sarasota-italian-restaurant-1920x907.jpg","d1u6rttDumSOyQuNDA92Jw==":"our-menu-sarasota-italian-restaurant-1-1920x907.jpg","5UyUQWHsim8/2ZhoVpzKpg==":"our-menu-sarasota-italian-restaurant-2-1920x907.jpg","2vQCS7nYT5LUfDAeoseHeA==":"our-menu-sarasota-italian-restaurant-3-1920x907.jpg","VYUXfRy5Avtq8ZZISi9+/g==":"cafe-towles-court-1920x815.jpg","cg3oGUN0g7UI+2YBRpVXtw==":"grilled-zuchinni-752x960.jpg","z6aiMV7zVbbPbhp4yEAMEA==":"italian-mojito-720x960.jpg","mXXgUFvYGXrdJJ+w/Om4RA==":"purple-potato-salad-720x960.jpg","mhVaAv+uk9iEKnrJqHUjzA==":"chicken-solare-720x960.jpg","fX28kwzdZSpkksrdgOthEg==":"grilled-zuchinni-720x960.jpg","Z3X+amlhXaV/LOVcMkOwiw==":"yelp-5star-585x200.png","P+0cEOUwPx6bxRyf1D2mWw==":"tripadvisor-5star-585x200.png","I3vfqZO2HNfVcesYqDWBEw==":"towles-court-restaurant-1-960x640.jpg","lw3EDCXNK8x9m4Oble4+fw==":"towles-court-dinner-1-960x720.jpg","UG0teESsuAffGzmXnfF3ZQ==":"main-entrance-1000x562.jpg","0Wjbr1+qo/JvpyzOGe3ohA==":"towles-court-cafe-700x933.jpg","y2ouIrirm6GpNf37QlHRVg==":"dinner-towles-court-700x933.jpg","1UZoMzbuURLa/RpcSdycfw==":"yelp-5star-293x100.png","wNrnCRfoEvEQGlzVVKIWiQ==":"tripadvisor-5star-293x100.png","B7cOw/VzKrrpnf5Tlfzoow==":"background1.jpg","O6VkPY81RWJoqUwqzyYwuQ==":"yelp-5star-1-585x200.png","24N2+BvjbegIvYpjKZ5KRQ==":"tripadvisor-5star-1-585x200.png","w89Y1shs/L2unRXl1n9TCw==":"italian-food-960x720.jpg","LRA0lizKJXP/QbN8kOOruA==":"italian-food-1-960x720.jpg","7drRPyMKEQaLLFdYaawzrA==":"italian-mojito-568x757.jpg","MUnI7NhNbH/FlwLtU+OsLw==":"bodhi-tree-towles-art-568x757.jpg","hmdT50146npLMcSRRXd43Q==":"sarasota-foodies-754x677.jpg","nLSP2qAT1oSwIuJj4M2PWA==":"img-8764-568x757.jpg","tyF2vf4zxDSeZRrsp+IdoA==":"sarasota-seafood-restaurant-400x600.jpg","PED/+E/niccjIfwsrbbxUw==":"vegetarian-conscious-srq-400x600.jpg","zNqDufzvdvv1LPnwJrDQtw==":"the-bodhi-tree-cafe-sarasota-400x600.jpg","f08zZabN33LpTiW3tjisoQ==":"patio-1000x562.jpg","ng1HYmG3ysfDyszwecUFtQ==":"vitelotte-homemade-gnocchi-1000x657.jpg","b7LU047VuF3ZZJyQD12syw==":"italian-restaurant-towles-court-1-960x714.jpg","TSJgve1lOfJq8rKPT3xVbA==":"pita-sampler-720x960.jpg","Zu4pvL1gHmA+rJBA36HMyw==":"downtown-sarasota-seafood-restaurant-754x977.jpg","57aItJVr9WiLoR1CUwMLRA==":"bodhi-tree-cafe-sarasota-dining-1920x907.jpg","szoLZgGIdlEmodLO6riydw==":"background7.jpg","3UIOaxchbEdRabWcQSi/tA==":"sarasota-restaurant-menu-1920x907.jpg","Q8X0B3KMAEZp3ljSHe7S2g==":"chef-oscar-570x739.jpg","sIOEZEo5XRvsqpRlTqGb1A==":"chef-oscar-754x977.jpg","RbYdY2U+2dyT72WP1tIVsQ==":"add%20pic%208-570x526.jpg","byNbgxW84SjrGU/KmHnc2A==":"sarasota-vegetarian-conscious-570x701.jpg","4fx7VXpOhR4Og7+18v0F2w==":"bodhi-tree-entrance-570x854.jpg","NybaI6dNshapxfKsifxyNA==":"purple-potato-salad-570x760.jpg","vPpD5Qd0dbJMd+rPARXTfQ==":"contessa-jewerly-570x428.jpg","cp7t5bAS7Pk7JO6G8nkXaQ==":"towles-court-dinner-570x428.jpg","nN5GlYakWBUr2026xsFfQg==":"towles-court-italian-570x760.jpg","GD13hOzXVv9GbUE2IaFNCA==":"contessa-jewerly-570x380.jpg","V9xWfwjVyFbhbeEWA+Tb4A==":"contessa-jewels-sarasota-570x457.jpg","1VSCCnlXLaXHrfhsoJOBZA==":"add%20pic%208-240x222.jpg","drkKh1758++w0AWDOJALxA==":"tripadvisor-5star-360x123.png","YnD71JJelee7n7OwxTxAgA==":"yelp-5star-360x123.png","UmYI0G08loqGH1hEpu0pOQ==":"bodhi-tree-cafe-menu-2220x1491.jpg"}